stringlifier/__init__.py
stringlifier/api.py
stringlifier/data/enhanced-c.bestType
stringlifier/data/enhanced-c.conf
stringlifier/data/enhanced-c.encodings
stringlifier/modules/__init__.py
stringlifier/modules/stringc.py
stringlifier/modules/stringc2.py
stringlifier/modules/training.py
stringlifier-0.1.1.5.dist-info/licenses/LICENSE
stringlifier-0.1.1.5.dist-info/METADATA
stringlifier-0.1.1.5.dist-info/WHEEL
stringlifier-0.1.1.5.dist-info/top_level.txt
stringlifier-0.1.1.5.dist-info/RECORD
