Metadata-Version: 2.4
Name: stringlifier
Version: 0.1.1.5
Summary: Python module for detecting password, api keys hashes and any other string that resembles a randomly generated character sequence.
Home-page: https://github.com/adobe/stringlifier
Author: Multiple authors
Author-email: tiberiu44@gmail.com
Classifier: Programming Language :: Python :: 3.0
Classifier: License :: OSI Approved :: Apache Software License
Classifier: Operating System :: OS Independent
License-File: LICENSE
Requires-Dist: ipdb>=0.13.4
Requires-Dist: nptyping>=2.5.0
Requires-Dist: numpy>=2.2.6
Requires-Dist: PyJWT>=2.10.1
Requires-Dist: setuptools>=80.7.1
Requires-Dist: torch>=2.7.0
Requires-Dist: tqdm>=4.67.1
Dynamic: author
Dynamic: author-email
Dynamic: classifier
Dynamic: description
Dynamic: description-content-type
Dynamic: home-page
Dynamic: license-file
Dynamic: requires-dist
Dynamic: summary
